tessera/__init__.py
tessera/main.py
tessera/secret.py
tessera/test.py
tessera_cli-0.1.3.dist-info/licenses/LICENSE.md
tessera_cli-0.1.3.dist-info/METADATA
tessera_cli-0.1.3.dist-info/WHEEL
tessera_cli-0.1.3.dist-info/entry_points.txt
tessera_cli-0.1.3.dist-info/top_level.txt
tessera_cli-0.1.3.dist-info/RECORD
