Metadata-Version: 2.4
Name: tessera.cli
Version: 0.1.3
Summary: Terminal-based password manager
Home-page: https://github.com/theawesomeaj/tessera
Author: TheAwesomeAJ
Classifier: Programming Language :: Python :: 3
Classifier: License :: OSI Approved :: MIT License
Classifier: Operating System :: OS Independent
Requires-Python: >=3.8
License-File: LICENSE.md
Requires-Dist: cryptography
Requires-Dist: rich
Dynamic: license-file
